kazquakersudp/__init__.py
kazquakersudp/_version.py
kazquakersudp/c_alert.py
kazquakersudp/c_alertsound.py
kazquakersudp/c_consumer.py
kazquakersudp/c_custom.py
kazquakersudp/c_forward.py
kazquakersudp/c_plot.py
kazquakersudp/c_printraw.py
kazquakersudp/c_rsam.py
kazquakersudp/c_telegram.py
kazquakersudp/c_testing.py
kazquakersudp/c_tweet.py
kazquakersudp/c_write.py
kazquakersudp/client.py
kazquakersudp/entry_points.py
kazquakersudp/helpers.py
kazquakersudp/p_producer.py
kazquakersudp/packetize.py
kazquakersudp/packetloss.py
kazquakersudp/raspberryshake.py
kazquakersudp/t_testdata.py
kazquakersudp/test.py
kazquakersudp/img/__init__.py
kazquakersudp/rs_sounds/__init__.py
rsudp/__init__.py
rsudp/_version.py
rsudp/c_alert.py
rsudp/c_alertsound.py
rsudp/c_consumer.py
rsudp/c_custom.py
rsudp/c_forward.py
rsudp/c_plot.py
rsudp/c_printraw.py
rsudp/c_rsam.py
rsudp/c_telegram.py
rsudp/c_testing.py
rsudp/c_tweet.py
rsudp/c_write.py
rsudp/client.py
rsudp/entry_points.py
rsudp/helpers.py
rsudp/p_producer.py
rsudp/packetize.py
rsudp/packetloss.py
rsudp/raspberryshake.py
rsudp/t_testdata.py
rsudp/test.py
rsudp/img/__init__.py
rsudp/img/icon.ico
rsudp/img/icon.png
rsudp/img/version1-01-small.png
rsudp/rs_sounds/__init__.py
rsudp/rs_sounds/alarm.mp3
rsudp/rs_sounds/beep.mp3
rsudp/rs_sounds/beeps.mp3
rsudp/rs_sounds/doorbell.mp3
rsudp/rs_sounds/japanes.mp3
rsudp/rs_sounds/sonar.mp3
rsudp/test/testdata.ms
kazquakersudp-1.1.3.dist-info/LICENSE
kazquakersudp-1.1.3.dist-info/METADATA
kazquakersudp-1.1.3.dist-info/WHEEL
kazquakersudp-1.1.3.dist-info/entry_points.txt
kazquakersudp-1.1.3.dist-info/top_level.txt
kazquakersudp-1.1.3.dist-info/RECORD
