Metadata-Version: 2.1
Name: kazquakersudp
Version: 1.1.3
Summary: Tools for receiving and interacting with Raspberry Shake UDP data
Home-page: https://github.com/kazquake/rsudp
Author: Rishat Sultanov
Author-email: rihasultanov@gmail.com
License: GPLv3
Classifier: License :: OSI Approved :: GNU General Public License v3 (GPLv3)
Classifier: Programming Language :: Python :: 3.6
Classifier: Programming Language :: Python :: 3.7
Classifier: Operating System :: OS Independent
Classifier: Framework :: Matplotlib
Classifier: Topic :: Scientific/Engineering :: Physics
Classifier: Intended Audience :: Education
Classifier: Intended Audience :: End Users/Desktop
Classifier: Intended Audience :: Science/Research
Classifier: Intended Audience :: Developers
Classifier: Natural Language :: English
Classifier: Development Status :: 5 - Production/Stable
License-File: LICENSE
Requires-Dist: obspy
Requires-Dist: numpy
Requires-Dist: matplotlib (<3.2)
Requires-Dist: pydub
Requires-Dist: twython
Requires-Dist: python-telegram-bot (<=13.11)
